{
    "common": {
        "name": "sigenergy",
        "version": "3.0.0",
        "news": {
            "3.0.0": {
                "en": "(ssbingo) feat: emergency gateway switching — automatic disconnection of external PV systems on grid failure; configurable stability timer; optional Telegram notifications",
                "de": "(ssbingo) Neu: Notabschaltung — automatische Trennung externer PV-Systeme bei Netzausfall; konfigurierbarer Stabilisierungs-Timer; optionale Telegram-Benachrichtigungen",
                "ru": "(ssbingo) Новое: аварийное отключение — автоматическое отключение внешних ФЭ-систем при пропадании сети; таймер стабилизации; уведомления Telegram",
                "pt": "(ssbingo) Novo: desligamento de emergência — desconexão automática de sistemas PV externos em caso de falha da rede; temporizador de estabilização; notificações Telegram",
                "nl": "(ssbingo) Nieuw: nooduitschakeling — automatisch loskoppelen van externe PV-systemen bij netuitval; stabilisatietimer; Telegram-meldingen",
                "fr": "(ssbingo) Nouveau : coupure d'urgence — déconnexion automatique des systèmes PV externes lors d'une coupure réseau ; minuterie de stabilisation ; notifications Telegram",
                "it": "(ssbingo) Nuovo: disconnessione d'emergenza — scollegamento automatico dei sistemi FV esterni in caso di mancanza di rete; timer di stabilizzazione; notifiche Telegram",
                "es": "(ssbingo) Nuevo: desconexión de emergencia — desconexión automática de sistemas FV externos ante fallos de red; temporizador de estabilización; notificaciones Telegram",
                "pl": "(ssbingo) Nowe: wyłączenie awaryjne — automatyczne odłączanie zewnętrznych systemów PV przy zaniku sieci; timer stabilizacji; powiadomienia Telegram",
                "uk": "(ssbingo) Нове: аварійне відключення — автоматичне відключення зовнішніх ФЕ-систем при зникненні мережі; таймер стабілізації; сповіщення Telegram",
                "zh-cn": "(ssbingo) 新功能：紧急断电 — 电网断电时自动断开外部光伏系统；稳定计时器；Telegram 通知"
            }
        },
        "titleLang": {
            "en": "Sigenergy Solar System",
            "de": "Sigenergy Solaranlage",
            "ru": "Солнечная система Sigenergy",
            "pt": "Sistema Solar Sigenergy",
            "nl": "Sigenergy Zonne-energiesysteem",
            "fr": "Système Solaire Sigenergy",
            "it": "Sistema Solare Sigenergy",
            "es": "Sistema Solar Sigenergy",
            "pl": "System Słoneczny Sigenergy",
            "uk": "Сонячна система Sigenergy",
            "zh-cn": "Sigenergy 太阳能系统"
        },
        "desc": {
            "en": "Adapter for Sigenergy solar energy systems (Hybrid Inverter, Battery, AC/DC Charger) via Modbus TCP/RTU",
            "de": "Adapter für Sigenergy Solarenergieanlagen (Hybrid Wechselrichter, Batterie, AC/DC Ladegerät) via Modbus TCP/RTU",
            "ru": "Адаптер для солнечных систем Sigenergy (гибридный инвертор, аккумулятор, зарядное устройство AC/DC) через Modbus TCP/RTU",
            "pt": "Adaptador para sistemas de energia solar Sigenergy (Inversor Híbrido, Bateria, Carregador AC/DC) via Modbus TCP/RTU",
            "nl": "Adapter voor Sigenergy zonne-energiesystemen (hybride omvormer, batterij, AC/DC-lader) via Modbus TCP/RTU",
            "fr": "Adaptateur pour les systèmes d'énergie solaire Sigenergy (onduleur hybride, batterie, chargeur AC/DC) via Modbus TCP/RTU",
            "it": "Adattatore per sistemi di energia solare Sigenergy (inverter ibrido, batteria, caricatore AC/DC) tramite Modbus TCP/RTU",
            "es": "Adaptador para sistemas de energía solar Sigenergy (inversor híbrido, batería, cargador AC/DC) a través de Modbus TCP/RTU",
            "pl": "Adapter dla systemów energii słonecznej Sigenergy (falownik hybrydowy, akumulator, ładowarka AC/DC) przez Modbus TCP/RTU",
            "uk": "Адаптер для сонячних енергетичних систем Sigenergy (гібридний інвертор, акумулятор, зарядний пристрій AC/DC) через Modbus TCP/RTU",
            "zh-cn": "通过Modbus TCP/RTU连接Sigenergy太阳能系统（混合逆变器、电池、AC/DC充电器）的适配器"
        },
        "authors": [
            "ioBroker Community"
        ],
        "keywords": [
            "sigenergy",
            "solar",
            "modbus",
            "energy",
            "inverter",
            "battery",
            "pv"
        ],
        "platform": "Javascript/Node.js",
        "icon": "sigenergy.png",
        "extIcon": "https://raw.githubusercontent.com/ssbingo/ioBroker.sigenergy/main/admin/sigenergy.png",
        "enabled": true,
        "readme": "https://github.com/ssbingo/ioBroker.sigenergy/blob/main/README.md",
        "loglevel": "info",
        "mode": "daemon",
        "type": "energy",
        "compact": true,
        "adminUI": {
            "config": "json"
        },
        "supportCustoms": false,
        "subscribable": false,
        "supportedMessages": {
            "custom": true
        },
        "tier": 2,
        "connectionType": "local",
        "dataSource": "poll",
        "dependencies": [
            {
                "js-controller": ">=6.0.11"
            }
        ],
        "globalDependencies": [
            {
                "admin": ">=7.6.20"
            }
        ],
        "licenseInformation": {
            "license": "MIT",
            "type": "free"
        }
    },
    "native": {
        "connectionType": "tcp",
        "tcpHost": "192.168.1.100",
        "tcpPort": 502,
        "serialPort": "/dev/ttyUSB0",
        "serialBaudRate": 9600,
        "serialDataBits": 8,
        "serialParity": "none",
        "serialStopBits": 1,
        "plantId": 247,
        "inverterId": 1,
        "acChargerId": 2,
        "dcChargerId": 3,
        "pollInterval": 10000,
        "timeout": 5000,
        "deviceType": "sigenstor",
        "hasAcCharger": false,
        "hasDcCharger": false,
        "hasBattery": true,
        "hasPv": true,
        "calcBatteryTimeToFull": true,
        "calcBatteryTimeRemaining": true,
        "calcBatteryDailyFull": true,
        "calcBatteryCoverageTime": true,
        "calcSelfConsumptionRate": true,
        "calcAutarkyRate": true,
        "calcPvYield": true,
        "calcGridFeedIn": true,
        "hasSigenMicro": false,
        "sigenMicroScanFrom": 10,
        "sigenMicroScanTo": 30,
        "sigenMicroDevices": "[]",
        "enableSmartLoads": false,
        "enableCumulativeEnergy": false,
        "enableGridCode": false,
        "enablePss": false,
        "pssSlaveId": 5,
        "enablePid": false,
        "pidSlaveId": 6,
        "enableEssPreheating": false,
        "hasEmergencyGateway": false,
        "emergencyDevice1Id": "",
        "emergencyDevice2Id": "",
        "emergencyDevice2Dir": "off",
        "emergencyDevice3Id": "",
        "emergencyDevice3Dir": "off",
        "emergencyDevice4Id": "",
        "emergencyDevice4Dir": "off",
        "emergencyStableDelay": 10,
        "emergencyTelegram": false,
        "emergencyTelegramInst": "",
        "emergencyTelegramChat": ""
    },
    "objects": [],
    "instanceObjects": [
        {
            "_id": "info",
            "type": "channel",
            "common": {
                "name": "Information"
            },
            "native": {}
        },
        {
            "_id": "info.connection",
            "type": "state",
            "common": {
                "name": "Connection status",
                "type": "boolean",
                "role": "indicator.connected",
                "read": true,
                "write": false,
                "def": false
            },
            "native": {}
        },
        {
            "_id": "info.scanProgress",
            "type": "state",
            "common": {
                "name": "SigenMicro scan progress",
                "type": "string",
                "role": "text",
                "read": true,
                "write": false,
                "def": ""
            },
            "native": {}
        },
        {
            "_id": "info.scanStatus",
            "type": "state",
            "common": {
                "name": "SigenMicro scan status",
                "type": "string",
                "role": "text",
                "read": true,
                "write": false,
                "def": "idle"
            },
            "native": {}
        },
        {
            "_id": "info.protocolLevel",
            "type": "state",
            "common": {
                "name": "Detected Modbus protocol level",
                "type": "string",
                "role": "text",
                "read": true,
                "write": false,
                "def": ""
            },
            "native": {}
        },
        {
            "_id": "info.modelType",
            "type": "state",
            "common": {
                "name": "Device model type (register 30500)",
                "type": "string",
                "role": "text",
                "read": true,
                "write": false,
                "def": ""
            },
            "native": {}
        }
    ]
}